.gitignore
.travis.yml
CHANGES
MANIFEST.in
README.rst
bootstrap.py
buildout.cfg
setup.py
isotoma/__init__.py
isotoma.buildout.basicauth.egg-info/PKG-INFO
isotoma.buildout.basicauth.egg-info/SOURCES.txt
isotoma.buildout.basicauth.egg-info/dependency_links.txt
isotoma.buildout.basicauth.egg-info/entry_points.txt
isotoma.buildout.basicauth.egg-info/namespace_packages.txt
isotoma.buildout.basicauth.egg-info/not-zip-safe
isotoma.buildout.basicauth.egg-info/requires.txt
isotoma.buildout.basicauth.egg-info/top_level.txt
isotoma/buildout/__init__.py
isotoma/buildout/basicauth/__init__.py
isotoma/buildout/basicauth/credentials.py
isotoma/buildout/basicauth/download.py
isotoma/buildout/basicauth/fetchers.py
isotoma/buildout/basicauth/protected_ext.py
isotoma/buildout/basicauth/tests/__init__.py
isotoma/buildout/basicauth/tests/test_credentials.py
isotoma/buildout/basicauth/tests/test_download.py
isotoma/buildout/basicauth/tests/test_fetchers.py