Metadata-Version: 1.0
Name: isotoma.buildout.basicauth
Version: 0.0.7
Summary: Buildout extension providing basic authentication support
Home-page: UNKNOWN
Author: John Carr
Author-email: john.carr@isotoma.com
License: Apache Public License
Keywords: buildout basicauth http authentication
Platform: UNKNOWN
